pureset.py
pureset-1.2.250709.0.dist-info/METADATA
pureset-1.2.250709.0.dist-info/WHEEL
pureset-1.2.250709.0.dist-info/licenses/LICENSE
pureset-1.2.250709.0.dist-info/RECORD
