Metadata-Version: 2.4
Name: pureset
Version: 1.2.250709.0
Summary: A simple collection type for homogeneous, immutable and ordered sequences.
Project-URL: Homepage, https://github.com/gabrielmsilva00/pureset
Project-URL: Issues, https://github.com/gabrielmsilva00/pureset/issues
Author-email: Gabriel Maia <gabrielmaia.silva00@gmail.com>
License-Expression: Apache-2.0
License-File: LICENSE
Classifier: License :: OSI Approved :: Apache Software License
Classifier: Operating System :: OS Independent
Classifier: Programming Language :: Python :: 3
Requires-Python: >=3.9
